loopquest/__init__.py
loopquest/api.py
loopquest/crud.py
loopquest/datasets.py
loopquest/eval.py
loopquest/private_api.py
loopquest/schema.py
loopquest/typing.py
loopquest/ui.py
loopquest/utils.py
loopquest/env/__init__.py
loopquest/env/api.py
loopquest/env/gym_wrappers.py
loopquest/env/space_utils.py
loopquest/policy/__init__.py
loopquest/policy/base.py
loopquest/policy/sb3_policy.py
loopquest-0.2.11.dist-info/LICENSE
loopquest-0.2.11.dist-info/METADATA
loopquest-0.2.11.dist-info/WHEEL
loopquest-0.2.11.dist-info/top_level.txt
loopquest-0.2.11.dist-info/RECORD
