Metadata-Version: 2.1
Name: loopquest
Version: 0.2.11
Summary: A Production Tool for Embodied AI.
Home-page: https://github.com/LoopMind-AI/loopquest
Author: LoopMind
Author-email: contactus@loopmind.ai
Classifier: Development Status :: 3 - Alpha
Classifier: Intended Audience :: Developers
Classifier: Programming Language :: Python :: 3.11
License-File: LICENSE
Requires-Dist: gymnasium >=0.29.0
Requires-Dist: huggingface-hub >=0.16.4
Requires-Dist: datasets >=2.14.4
Requires-Dist: python-dotenv >=1.0.0
Requires-Dist: stable-baselines3 >=2.2.1
Requires-Dist: huggingface-sb3 >=3.0
Requires-Dist: pydantic >=2.1.1
Provides-Extra: dev
Requires-Dist: pytest ; extra == 'dev'
Requires-Dist: twine ; extra == 'dev'
Provides-Extra: mujoco
Requires-Dist: mujoco >=2.1.5 ; extra == 'mujoco'
Requires-Dist: imageio >=2.14.1 ; extra == 'mujoco'
Provides-Extra: mujoco-py
Requires-Dist: mujoco-py <2.2,>=2.1 ; extra == 'mujoco-py'
Requires-Dist: cython <3 ; extra == 'mujoco-py'
Provides-Extra: rl
Requires-Dist: ale-py >=0.8 ; extra == 'rl'
Requires-Dist: box2d-py ==2.3.5 ; extra == 'rl'
Requires-Dist: pygame >=2.1.3 ; extra == 'rl'
Requires-Dist: swig ==4.* ; extra == 'rl'
